{
    "bookId": "sozler",
    "pageId": "sozler-0280",
    "pageIndex": 280,
    "sectionId": "sozler-section-056",
    "header": {
        "title": "[1] Hâşiye: Hüseyin-i Cisrî “Risale-i Hamîdiye”sinde yüz on dört işaratı, o kitaplardan çıkarmıştır. Tahriften sonra bu kadar bulunsa elbette daha evvel çok tasrihat varmış.",
        "sticky": true
    },
    "segments": [
        {
            "segmentId": "sozler-0280-header",
            "type": "heading",
            "text": "[1] Hâşiye: Hüseyin-i Cisrî “Risale-i Hamîdiye”sinde yüz on dört işaratı, o kitaplardan çıkarmıştır. Tahriften sonra bu kadar bulunsa elbette daha evvel çok tasrihat varmış.",
            "lang": "tr"
        }
    ]
}