{
    "bookId": "sozler",
    "pageId": "sozler-0375",
    "pageIndex": 375,
    "sectionId": "sozler-section-069",
    "header": {
        "title": "Yirmi Dördüncü Söz",
        "sticky": true
    },
    "segments": [
        {
            "segmentId": "sozler-0375-001",
            "type": "paragraph",
            "text": "Üçüncüsü: Enaniyeti bırakmayan ve âsâra dalan ve yalnız istidlaliyle hakikate giden…",
            "lang": "tr"
        },
        {
            "segmentId": "sozler-0375-002",
            "type": "paragraph",
            "text": "Ve ilim ve hikmetle ve akıl ve marifetle hakikati aramaya giden…",
            "lang": "tr"
        },
        {
            "segmentId": "sozler-0375-003",
            "type": "paragraph",
            "text": "Ve iman ve Kur’an ile fakr ve ubudiyetle hakikate çabuk giden ayrı ayrı istidatta bulunan üç taifenin hikmet-i ihtilaflarına işaret eden temsillerdir.",
            "lang": "tr"
        },
        {
            "segmentId": "sozler-0375-004",
            "type": "paragraph",
            "text": "İşte şu üç tabakanın terakkiyatındaki sırrı ve geniş hikmeti; zühre, katre, reşha unvanları altında bir temsil ile bir derece göstereceğiz.",
            "lang": "tr"
        },
        {
            "segmentId": "sozler-0375-005",
            "type": "paragraph",
            "text": "Mesela, güneşin kendi Hâlık’ının izniyle ve emriyle üç çeşit tecellisi ve in’ikası ve ifazası var: Birisi çiçeklere, birisi kamere ve seyyarelere, birisi şişe ve su gibi parlaklara verdiği ayrı ayrı in’ikaslarıdır.",
            "lang": "tr"
        },
        {
            "segmentId": "sozler-0375-006",
            "type": "paragraph",
            "text": "Birincisi üç tarzdadır:",
            "lang": "tr"
        },
        {
            "segmentId": "sozler-0375-007",
            "type": "paragraph",
            "text": "Biri: Küllî ve umumî bir tecelli ve in’ikasıdır ki bütün çiçeklere birden ifazasıdır.",
            "lang": "tr"
        }
    ]
}