{
    "bookId": "sozler",
    "pageId": "sozler-0638",
    "pageIndex": 638,
    "sectionId": "sozler-section-099",
    "header": {
        "title": "ON DOKUZUNCU VE OTUZ BİRİNCİ SÖZLERİN ZEYLİ",
        "sticky": true
    },
    "segments": [
        {
            "segmentId": "sozler-0638-001",
            "type": "paragraph",
            "text": "عَلَيْهِ وَ عَلٰى اٰلِهِ الصَّلَاةُ وَ التَّسْلٖيمَاتُ مِلْأَ الْاَرْضِ وَ السَّمٰوَاتِ",
            "lang": "ar"
        },
        {
            "segmentId": "sozler-0638-002",
            "type": "paragraph",
            "text": "سُبْحَانَكَ لَا عِلْمَ لَنَٓا اِلَّا مَا عَلَّمْتَنَٓا اِنَّكَ اَنْتَ الْعَلٖيمُ الْحَكٖيمُ",
            "lang": "ar"
        },
        {
            "segmentId": "sozler-0638-003",
            "type": "paragraph",
            "text": "اَللّٰهُمَّ بِحَقِّ مَنِ انْشَقَّ الْقَمَرُ بِاِشَارَتِهِ اجْعَلْ قَلْبٖى وَ قُلُوبَ طَلَبَةِ رَسَائِلِ النُّورِ الصَّادِقٖينَ كَالْقَمَرِ فٖى مُقَابَلَةِ شَمْسِ الْقُرْاٰنِ اٰمٖينَ اٰمٖينَ",
            "lang": "ar"
        }
    ]
}