{
    "bookId": "sozler",
    "pageId": "sozler-0833",
    "pageIndex": 833,
    "sectionId": "sozler-section-175",
    "header": {
        "title": "İcad ve cem’-i ezdadda büyük bir hikmet var. Kudret elinde şems ve zerre birdir.",
        "sticky": true
    },
    "segments": [
        {
            "segmentId": "sozler-0833-001",
            "type": "paragraph",
            "text": "Ger zemherir olmazsa o da ihrak edemez. O Hallak-ı Lemyezel, halk-ı ezdad içinde hikmetini gösterdi. Haşmeti etti zuhur.",
            "lang": "tr"
        },
        {
            "segmentId": "sozler-0833-002",
            "type": "paragraph",
            "text": "O Kadîr-i Lâyezal, cem’-i ezdad içinde iktidarı gösterdi. Azamet etti zuhur. Madem o kudret-i İlahî lâzıme-i zatî olur",
            "lang": "tr"
        },
        {
            "segmentId": "sozler-0833-003",
            "type": "paragraph",
            "text": "O Zat-ı Ezelî’ye hem zarure-i nâşie; onda zıddı olamaz, acz tahallül edemez, onda meratib olamaz, her şeye nisbeti bir, hiçbir şey ağır olmuyor.",
            "lang": "tr"
        },
        {
            "segmentId": "sozler-0833-004",
            "type": "paragraph",
            "text": "O kudretin ziyasına güneş mişkât olmuştur. Bu mişkâtın nuruna deniz yüzü âyine, şebnemlerin gözleri birer mir’at olmuştur.",
            "lang": "tr"
        },
        {
            "segmentId": "sozler-0833-005",
            "type": "paragraph",
            "text": "Denizin geniş yüzü, gösterdiği güneşi çin-i cebînindeki katreler de gösterir, şebnemin küçük gözü yıldız gibi parlıyor.",
            "lang": "tr"
        },
        {
            "segmentId": "sozler-0833-006",
            "type": "paragraph",
            "text": "Aynı hüviyet tutar; şebnem, deniz bir olur güneşin nazarında, kudreti tanzir eder; şebnemin göz bebeği küçücük bir güneştir.",
            "lang": "tr"
        },
        {
            "segmentId": "sozler-0833-007",
            "type": "paragraph",
            "text": "Şu muhteşem güneş de küçücük bir şebnemdir; göz bebeği bir nurdur ki şems-i kudretten gelir, o kudrete kamer olur.",
            "lang": "tr"
        }
    ]
}