{
    "bookId": "sozler",
    "pageId": "sozler-0871",
    "pageIndex": 871,
    "sectionId": "sozler-section-198",
    "header": {
        "title": "Îcaz ile beyan i’caz-ı Kur’an",
        "sticky": true
    },
    "segments": [
        {
            "segmentId": "sozler-0871-001",
            "type": "paragraph",
            "text": "Ahkâmdaki istiab: Şu hârika şeriat ondan olmuş istinbat. Saadet-i dâreynin bütün desatirini, bütün esbab-ı emni,",
            "lang": "tr"
        },
        {
            "segmentId": "sozler-0871-002",
            "type": "paragraph",
            "text": "İçtimaî hayatın bütün revabıtını, vesail-i terbiye, hakaik-i ahvali birden tazammun etmiş onun tarz-ı beyanı…",
            "lang": "tr"
        },
        {
            "segmentId": "sozler-0871-003",
            "type": "paragraph",
            "text": "İlmindeki istiğrak: Hem ulûm-u kevniye hem ulûm-u İlahî, onda meratib-i delâlat, rumuz ile işarat, sureler surlarında cem’etmiştir cinanı.",
            "lang": "tr"
        },
        {
            "segmentId": "sozler-0871-004",
            "type": "paragraph",
            "text": "Makasıd ve gayatta: Muvazenet, ıttırad, fıtrat desatirine mutabakat, ittihat; tamam müraat etmiş, hıfzeylemiş mizanı.",
            "lang": "tr"
        },
        {
            "segmentId": "sozler-0871-005",
            "type": "paragraph",
            "text": "İşte lafzın ihatasında, mananın vüs’atinde, hükmün istiabında, ilmin istiğrakında, muvazene-i gayatta câmiiyet-i pür-şanı!..",
            "lang": "tr"
        },
        {
            "segmentId": "sozler-0871-006",
            "type": "paragraph",
            "text": "Dördüncü Unsur ise: Her asrın derece-i fehmine, edebî rütbesine hem her asırdaki tabakata, derece-i istidat, rütbe-i kabiliyet nisbetinde ediyor bir ifaza-i nurani.",
            "lang": "tr"
        },
        {
            "segmentId": "sozler-0871-007",
            "type": "paragraph",
            "text": "Her asra, her asırdaki her tabakaya kapısı küşade. Güya her demde, her yerde taze nâzil oluyor o Kelâm-ı Rahmanî.",
            "lang": "tr"
        }
    ]
}